main.py
src/__init__.py
src/cli/__init__.py
src/cli/parser.py
src/constants/__init__.py
src/constants/books.py
src/constants/chapters.py
src/constants/cli.py
src/constants/copyright.py
src/constants/translations.py
src/constants/version.py
src/core/__init__.py
src/core/downloader.py
src/formatters/__init__.py
src/formatters/csv.py
src/formatters/json.py
src/formatters/xml.py
src/formatters/yaml.py
src/processors/__init__.py
src/processors/bible.py
src/processors/book.py
src/processors/books.py
src/processors/translations.py
src/tests/__init__.py
src/tests/conftest.py
src/tests/test_constants.py
src/tests/test_core.py
src/tests/test_utils.py
src/utils/__init__.py
src/utils/formatting.py
src/utils/logging.py
bygod-3.2.0.dist-info/LICENSE
bygod-3.2.0.dist-info/METADATA
bygod-3.2.0.dist-info/WHEEL
bygod-3.2.0.dist-info/entry_points.txt
bygod-3.2.0.dist-info/top_level.txt
bygod-3.2.0.dist-info/RECORD
