Metadata-Version: 2.1
Name: bygod
Version: 3.2.0
Summary: A comprehensive, truly asynchronous tool for downloading Bible translations from BibleGateway.com
Author-email: ByGoD Team <ByGoD@rapdirabbit.software>
Maintainer-email: ByGoD Team <ByGoD@rapdirabbit.software>
License: MIT
Project-URL: Homepage, https://github.com/Christ-Is-The-King/bygod
Project-URL: Documentation, https://github.com/Christ-Is-The-King/bygod#readme
Project-URL: Repository, https://github.com/Christ-Is-The-King/bygod
Project-URL: Bug Tracker, https://github.com/Christ-Is-The-King/bygod/issues
Keywords: bible,download,biblegateway,async,scripture,religion,json,csv,xml,yaml
Classifier: Development Status :: 5 - Production/Stable
Classifier: Intended Audience :: Developers
Classifier: Intended Audience :: Religion
Classifier: Operating System :: OS Independent
Classifier: Programming Language :: Python :: 3
Classifier: Programming Language :: Python :: 3.8
Classifier: Programming Language :: Python :: 3.9
Classifier: Programming Language :: Python :: 3.10
Classifier: Programming Language :: Python :: 3.11
Classifier: Programming Language :: Python :: 3.12
Classifier: Topic :: Internet :: WWW/HTTP
Classifier: Topic :: Software Development :: Libraries :: Python Modules
Classifier: Topic :: Text Processing :: Markup :: HTML
Classifier: Topic :: Utilities
Requires-Python: >=3.8
License-File: LICENSE
Requires-Dist: aiohttp>=3.8.0
Requires-Dist: beautifulsoup4>=4.11.0
Requires-Dist: colorlog>=6.7.0
Requires-Dist: pyyaml>=6.0
Requires-Dist: lxml>=4.9.0
Requires-Dist: meaningless>=1.2.0
Provides-Extra: dev
Requires-Dist: pytest; extra == "dev"
Requires-Dist: black; extra == "dev"
Requires-Dist: flake8; extra == "dev"
Requires-Dist: isort; extra == "dev"
Requires-Dist: mypy; extra == "dev"
Requires-Dist: pylint; extra == "dev"
Requires-Dist: bandit; extra == "dev"
Requires-Dist: pydocstyle; extra == "dev"
Requires-Dist: vulture; extra == "dev"
Requires-Dist: radon; extra == "dev"
Requires-Dist: safety; extra == "dev"
Requires-Dist: pre-commit; extra == "dev"
Requires-Dist: twine; extra == "dev"
Requires-Dist: build; extra == "dev"
